flexi_path/__init__.py
flexi_path-4.0.0.dist-info/METADATA
flexi_path-4.0.0.dist-info/WHEEL
flexi_path-4.0.0.dist-info/top_level.txt
flexi_path-4.0.0.dist-info/RECORD
