Metadata-Version: 2.1
Name: flexi-path
Version: 4.0.0
Summary: a package
Author-email: Coffeechili <coffee@chi.li>
Requires-Python: >=3.8
